{"v":"5.5.2","fr":29.9700012207031,"ip":0,"op":122.000004969162,"w":375,"h":812,"nm":"Comp 3","ddd":0,"assets":[],"layers":[{"ddd":0,"ind":1,"ty":4,"nm":"Layer 3 Outlines","sr":1,"ks":{"o":{"a":1,"k":[{"i":{"x":[0.833],"y":[0.833]},"o":{"x":[0.167],"y":[0.167]},"t":2,"s":[19]},{"t":9.00000036657752,"s":[100]}],"ix":11},"r":{"a":0,"k":0,"ix":10},"p":{"a":0,"k":[121,436.835,0],"ix":2},"a":{"a":0,"k":[0,0,0],"ix":1},"s":{"a":0,"k":[100,100,100],"ix":6}},"ao":0,"shapes":[{"ty":"gr","it":[{"ind":0,"ty":"sh","ix":1,"ks":{"a":0,"k":{"i":[[-0.095,0.002],[-0.041,-3.441],[0.001,-0.064],[3.393,-0.143],[0.339,3.335],[-3.516,0.24]],"o":[[3.442,-0.041],[0,0.065],[0.034,3.396],[-3.352,-0.01],[-0.24,-3.517],[0.095,-0.006]],"v":[[0.059,-6.329],[6.365,-0.173],[6.364,0.02],[0.337,6.37],[-6.158,0.484],[-0.225,-6.316]],"c":true},"ix":2},"nm":"Path 1","mn":"ADBE Vector Shape - Group","hd":false},{"ty":"fl","c":{"a":0,"k":[1,1,1,1],"ix":4},"o":{"a":0,"k":100,"ix":5},"r":1,"bm":0,"nm":"Fill 1","mn":"ADBE Vector Graphic - Fill","hd":false},{"ty":"tr","p":{"a":0,"k":[6.648,6.621],"ix":2},"a":{"a":0,"k":[0,0],"ix":1},"s":{"a":0,"k":[100,100],"ix":3},"r":{"a":0,"k":0,"ix":6},"o":{"a":0,"k":100,"ix":7},"sk":{"a":0,"k":0,"ix":4},"sa":{"a":0,"k":0,"ix":5},"nm":"Transform"}],"nm":"Group 1","np":2,"cix":2,"bm":0,"ix":1,"mn":"ADBE Vector Group","hd":false}],"ip":2.00000008146167,"op":902.000036739213,"st":2.00000008146167,"bm":0},{"ddd":0,"ind":2,"ty":4,"nm":"Layer 4 Outlines","sr":1,"ks":{"o":{"a":0,"k":100,"ix":11},"r":{"a":0,"k":0,"ix":10},"p":{"a":0,"k":[194.028,471.194,0],"ix":2},"a":{"a":0,"k":[64.748,18.391,0],"ix":1},"s":{"a":0,"k":[100,100,100],"ix":6}},"ao":0,"hasMask":true,"masksProperties":[{"inv":false,"mode":"a","pt":{"a":1,"k":[{"i":{"x":0.833,"y":0.833},"o":{"x":0.167,"y":0.167},"t":7,"s":[{"i":[[0,0],[0,0],[0,0],[0,0]],"o":[[0,0],[0,0],[0,0],[0,0]],"v":[[-1.447,-2.586],[-1.447,42.196],[-1.78,42.196],[-1.78,-2.586]],"c":true}]},{"t":18.000000733155,"s":[{"i":[[0,0],[0,0],[0,0],[0,0]],"o":[[0,0],[0,0],[0,0],[0,0]],"v":[[-1.447,-2.586],[-1.447,42.196],[133.72,42.196],[133.72,-2.586]],"c":true}]}],"ix":1},"o":{"a":0,"k":100,"ix":3},"x":{"a":0,"k":0,"ix":4},"nm":"Mask 1"}],"shapes":[{"ty":"gr","it":[{"ind":0,"ty":"sh","ix":1,"ks":{"a":0,"k":{"i":[[19.865,-0.478],[17.753,16.706],[-1.653,1.762],[-2.644,-2.659],[-16.938,-1.692],[-17.564,16.194],[-1.871,0.205],[-1.09,-2.014],[1.846,-1.87],[3.411,-2.441]],"o":[[-23.5,-0.034],[-2.817,-2.652],[2.225,-2.369],[11.911,12.161],[23.641,2.58],[1.317,-1.215],[2.247,-0.44],[1.428,2.206],[-2.889,3.041],[-15.292,11.258]],"v":[[0.573,18.141],[-61.68,-7.001],[-62.355,-15.771],[-53.619,-15.404],[-8.965,6.04],[53.035,-14.561],[57.461,-17.366],[63.07,-14.719],[62.355,-7.742],[52.883,0.501]],"c":true},"ix":2},"nm":"Path 1","mn":"ADBE Vector Shape - Group","hd":false},{"ty":"fl","c":{"a":0,"k":[1,1,1,1],"ix":4},"o":{"a":0,"k":100,"ix":5},"r":1,"bm":0,"nm":"Fill 1","mn":"ADBE Vector Graphic - Fill","hd":false},{"ty":"tr","p":{"a":0,"k":[64.747,18.391],"ix":2},"a":{"a":0,"k":[0,0],"ix":1},"s":{"a":0,"k":[100,100],"ix":3},"r":{"a":0,"k":0,"ix":6},"o":{"a":0,"k":100,"ix":7},"sk":{"a":0,"k":0,"ix":4},"sa":{"a":0,"k":0,"ix":5},"nm":"Transform"}],"nm":"Group 1","np":2,"cix":2,"bm":0,"ix":1,"mn":"ADBE Vector Group","hd":false},{"ty":"tm","s":{"a":0,"k":0,"ix":1},"e":{"a":0,"k":100,"ix":2},"o":{"a":0,"k":0,"ix":3},"m":2,"ix":2,"nm":"Trim Paths 1","mn":"ADBE Vector Filter - Trim","hd":false}],"ip":7.00000028511585,"op":907.000036942867,"st":7.00000028511585,"bm":0},{"ddd":0,"ind":3,"ty":4,"nm":"Layer 1 Outlines","sr":1,"ks":{"o":{"a":0,"k":100,"ix":11},"r":{"a":1,"k":[{"i":{"x":[0.833],"y":[0.833]},"o":{"x":[0.167],"y":[0.167]},"t":15,"s":[358]},{"t":23.0000009368092,"s":[0]}],"ix":10},"p":{"a":1,"k":[{"i":{"x":0.833,"y":0.833},"o":{"x":0.167,"y":0.167},"t":15,"s":[398.057,445.31,0],"to":[-22.667,0,0],"ti":[22.667,0,0]},{"t":23.0000009368092,"s":[262.057,445.31,0]}],"ix":2},"a":{"a":0,"k":[8.021,8.142,0],"ix":1},"s":{"a":0,"k":[100,100,100],"ix":6}},"ao":0,"shapes":[{"ty":"gr","it":[{"ind":0,"ty":"sh","ix":1,"ks":{"a":0,"k":{"i":[[-0.799,-0.184],[-2.752,-1.854],[0.392,-0.614],[1.562,-2.332],[1.158,1.061],[1.922,1.6],[-0.822,1.241],[-1.55,2.343]],"o":[[2.609,1.616],[0.663,0.445],[-1.515,2.364],[-0.669,1],[-1.835,-1.688],[-0.64,-0.532],[1.553,-2.344],[0.222,-0.334]],"v":[[-1.115,-7.708],[7.108,-2.554],[6.94,-0.54],[2.303,6.492],[-0.137,6.831],[-5.98,2.131],[-6.949,-0.086],[-2.305,-7.129]],"c":true},"ix":2},"nm":"Path 1","mn":"ADBE Vector Shape - Group","hd":false},{"ty":"fl","c":{"a":0,"k":[1,1,1,1],"ix":4},"o":{"a":0,"k":100,"ix":5},"r":1,"bm":0,"nm":"Fill 1","mn":"ADBE Vector Graphic - Fill","hd":false},{"ty":"tr","p":{"a":0,"k":[8.021,8.142],"ix":2},"a":{"a":0,"k":[0,0],"ix":1},"s":{"a":0,"k":[100,100],"ix":3},"r":{"a":0,"k":0,"ix":6},"o":{"a":0,"k":100,"ix":7},"sk":{"a":0,"k":0,"ix":4},"sa":{"a":0,"k":0,"ix":5},"nm":"Transform"}],"nm":"Group 1","np":2,"cix":2,"bm":0,"ix":1,"mn":"ADBE Vector Group","hd":false}],"ip":15.0000006109625,"op":915.000037268714,"st":15.0000006109625,"bm":0},{"ddd":0,"ind":4,"ty":4,"nm":"Layer 2 Outlines","sr":1,"ks":{"o":{"a":0,"k":100,"ix":11},"r":{"a":0,"k":0,"ix":10},"p":{"a":0,"k":[193.746,397.333,0],"ix":2},"a":{"a":0,"k":[72.591,38.642,0],"ix":1},"s":{"a":1,"k":[{"i":{"x":[0.833,0.833,0.833],"y":[0.833,0.833,0.833]},"o":{"x":[0.167,0.167,0.167],"y":[0.167,0.167,0.167]},"t":0,"s":[11,11,100]},{"t":7.00000028511585,"s":[100,100,100]}],"ix":6}},"ao":0,"shapes":[{"ty":"gr","it":[{"ind":0,"ty":"sh","ix":1,"ks":{"a":0,"k":{"i":[[1.493,0.557],[-0.016,-4.618],[-2.035,-0.45],[-0.364,2.124]],"o":[[-3.579,-1.334],[0.47,1.074],[2.012,0.451],[0.305,-1.781]],"v":[[2.252,-4.178],[-3.948,1.396],[-2.651,5.061],[4.381,-0.852]],"c":true},"ix":2},"nm":"Path 1","mn":"ADBE Vector Shape - Group","hd":false},{"ty":"fl","c":{"a":0,"k":[0.732999973671,0.902000038297,0.016000001571,1],"ix":4},"o":{"a":0,"k":100,"ix":5},"r":1,"bm":0,"nm":"Fill 1","mn":"ADBE Vector Graphic - Fill","hd":false},{"ty":"tr","p":{"a":0,"k":[140.246,33.681],"ix":2},"a":{"a":0,"k":[0,0],"ix":1},"s":{"a":0,"k":[100,100],"ix":3},"r":{"a":0,"k":0,"ix":6},"o":{"a":0,"k":100,"ix":7},"sk":{"a":0,"k":0,"ix":4},"sa":{"a":0,"k":0,"ix":5},"nm":"Transform"}],"nm":"Group 1","np":2,"cix":2,"bm":0,"ix":1,"mn":"ADBE Vector Group","hd":false},{"ty":"gr","it":[{"ind":0,"ty":"sh","ix":1,"ks":{"a":0,"k":{"i":[[0,-3.88],[0,0],[-0.027,-2.726],[-0.055,-1.667],[-1.385,-0.141],[0.021,1.744],[0,6.712],[4.485,0.1],[-0.055,-1.7]],"o":[[0,0],[0,2.726],[0.016,1.666],[1.375,-0.222],[2.247,0.521],[-0.08,-6.711],[0.001,-4.356],[-1.682,-0.037],[0.127,3.875]],"v":[[-3.261,0.063],[-3.279,0.063],[-3.271,8.243],[-3.112,13.243],[1.046,13.121],[3.335,10.878],[3.304,-9.257],[-1.18,-13.605],[-3.301,-11.574]],"c":true},"ix":2},"nm":"Path 1","mn":"ADBE Vector Shape - Group","hd":false},{"ty":"fl","c":{"a":0,"k":[0.732999973671,0.902000038297,0.016000001571,1],"ix":4},"o":{"a":0,"k":100,"ix":5},"r":1,"bm":0,"nm":"Fill 1","mn":"ADBE Vector Graphic - Fill","hd":false},{"ty":"tr","p":{"a":0,"k":[140.546,14.964],"ix":2},"a":{"a":0,"k":[0,0],"ix":1},"s":{"a":0,"k":[100,100],"ix":3},"r":{"a":0,"k":0,"ix":6},"o":{"a":0,"k":100,"ix":7},"sk":{"a":0,"k":0,"ix":4},"sa":{"a":0,"k":0,"ix":5},"nm":"Transform"}],"nm":"Group 2","np":2,"cix":2,"bm":0,"ix":2,"mn":"ADBE Vector Group","hd":false},{"ty":"gr","it":[{"ind":0,"ty":"sh","ix":1,"ks":{"a":0,"k":{"i":[[-3.244,0.079],[-3.246,0],[0,0],[-3.35,-0.047],[0.058,1.467],[0.842,5.308],[5.365,0.949],[-0.072,-4.915],[-1.76,-0.066],[-0.1,-4.223],[-0.127,-1.558],[1.869,0.048],[4.184,0.142],[-0.128,-1.425]],"o":[[3.244,-0.079],[0,0],[3.352,0],[1.227,0.016],[-0.209,-5.329],[-0.859,-5.422],[-4.914,-0.868],[0.022,1.501],[4.299,0.159],[0.037,1.569],[0.162,1.97],[-4.186,-0.107],[-2.72,-0.092],[0.133,1.477]],"v":[[-9.482,13.778],[0.257,13.76],[0.255,13.725],[10.307,13.741],[12.283,12.057],[11.883,-3.934],[2.975,-12.989],[-2.284,-8.541],[-0.273,-6.291],[5.594,-0.291],[5.585,4.416],[3.046,6.886],[-9.518,6.816],[-11.538,9.985]],"c":true},"ix":2},"nm":"Path 1","mn":"ADBE Vector Shape - Group","hd":false},{"ty":"fl","c":{"a":0,"k":[0.732999973671,0.902000038297,0.016000001571,1],"ix":4},"o":{"a":0,"k":100,"ix":5},"r":1,"bm":0,"nm":"Fill 1","mn":"ADBE Vector Graphic - Fill","hd":false},{"ty":"tr","p":{"a":0,"k":[13.136,26.24],"ix":2},"a":{"a":0,"k":[0,0],"ix":1},"s":{"a":0,"k":[100,100],"ix":3},"r":{"a":0,"k":0,"ix":6},"o":{"a":0,"k":100,"ix":7},"sk":{"a":0,"k":0,"ix":4},"sa":{"a":0,"k":0,"ix":5},"nm":"Transform"}],"nm":"Group 3","np":2,"cix":2,"bm":0,"ix":3,"mn":"ADBE Vector Group","hd":false},{"ty":"gr","it":[{"ind":0,"ty":"sh","ix":1,"ks":{"a":0,"k":{"i":[[3.016,1.21],[3.145,1.125],[-0.146,1.115],[-0.94,0.03],[-2.239,-0.553],[-1.519,4.119],[1.483,0.49],[5.064,-1.952],[-0.025,-3.144],[-5.175,-1.4],[-1.84,-0.373],[-0.006,-1.449],[1.239,-0.2],[2.805,1.475],[0.651,-1.774],[-4.969,-1.249],[-2.383,0.128],[-0.728,-0.008],[-1.607,0.776],[-0.049,3.034]],"o":[[-3.071,-1.455],[-0.937,-0.335],[0.143,-1.093],[2.297,-0.2],[4.215,1.267],[0.583,-1.584],[-4.959,-1.639],[-3.001,0.939],[-0.126,4.278],[1.813,0.49],[1.299,0.262],[0.009,1.618],[-3.13,0.496],[-1.885,-0.961],[-1.76,4.803],[2.295,0.657],[0.496,0],[1.784,-0.044],[2.848,-1.045],[0.219,-3.242]],"v":[[7.174,-0.949],[-2.458,-3.616],[-4.215,-5.48],[-2.049,-6.901],[4.801,-6.368],[10.458,-9.301],[9.214,-12.152],[-5.818,-12.705],[-10.827,-5.832],[-3.464,2.533],[2.036,3.756],[4.719,5.918],[1.919,7.802],[-7.223,6.293],[-10.254,7.613],[-7.114,13.729],[-0.048,14.529],[1.91,14.531],[7.055,13.287],[11.863,6.518]],"c":true},"ix":2},"nm":"Path 1","mn":"ADBE Vector Shape - Group","hd":false},{"ty":"fl","c":{"a":0,"k":[0.732999973671,0.902000038297,0.016000001571,1],"ix":4},"o":{"a":0,"k":100,"ix":5},"r":1,"bm":0,"nm":"Fill 1","mn":"ADBE Vector Graphic - Fill","hd":false},{"ty":"tr","p":{"a":0,"k":[44.357,60.173],"ix":2},"a":{"a":0,"k":[0,0],"ix":1},"s":{"a":0,"k":[100,100],"ix":3},"r":{"a":0,"k":0,"ix":6},"o":{"a":0,"k":100,"ix":7},"sk":{"a":0,"k":0,"ix":4},"sa":{"a":0,"k":0,"ix":5},"nm":"Transform"}],"nm":"Group 4","np":2,"cix":2,"bm":0,"ix":4,"mn":"ADBE Vector Group","hd":false},{"ty":"gr","it":[{"ind":0,"ty":"sh","ix":1,"ks":{"a":0,"k":{"i":[[1.45,-0.683],[-0.337,2.053],[-2.369,0.076],[0,-3.468]],"o":[[-3.869,-0.028],[0.528,-3.183],[4.257,-0.136],[-0.004,3.912]],"v":[[0.666,7.728],[-5.031,4.435],[0.589,1.243],[5.189,5.028]],"c":true},"ix":2},"nm":"Path 1","mn":"ADBE Vector Shape - Group","hd":false},{"ind":1,"ty":"sh","ix":2,"ks":{"a":0,"k":{"i":[[0.234,4.918],[5.207,1.183],[2.079,-0.306],[0.125,-6.526],[-0.122,-0.225],[-1.591,0.341],[-2.736,-1.246],[0.245,-1.081],[0.7,0.033],[2.725,-0.776],[-0.081,-4.217],[-4.144,-1.165],[-5.2,1.523],[0.175,1.078]],"o":[[-0.258,-5.369],[-2.052,-0.454],[-6.444,0.89],[-0.002,0.092],[1.532,-0.485],[2.777,-0.59],[1.06,0.324],[-0.3,1.229],[-2.819,-0.283],[-4.298,1.445],[0.072,3.765],[5.311,1.494],[1.063,-0.251],[-0.042,-4.929]],"v":[[11.779,-4.755],[3.678,-14.089],[-2.57,-14.313],[-9.701,-6.236],[-9.484,-5.827],[-4.825,-7.271],[3.5,-6.994],[4.946,-4.503],[2.846,-4.039],[-5.546,-3.293],[-11.973,5.307],[-5.465,13.125],[10.303,12.388],[11.879,10.029]],"c":true},"ix":2},"nm":"Path 2","mn":"ADBE Vector Shape - Group","hd":false},{"ty":"mm","mm":1,"nm":"Merge Paths 1","mn":"ADBE Vector Filter - Merge","hd":false},{"ty":"fl","c":{"a":0,"k":[0.732999973671,0.902000038297,0.016000001571,1],"ix":4},"o":{"a":0,"k":100,"ix":5},"r":1,"bm":0,"nm":"Fill 1","mn":"ADBE Vector Graphic - Fill","hd":false},{"ty":"tr","p":{"a":0,"k":[101.718,60.868],"ix":2},"a":{"a":0,"k":[0,0],"ix":1},"s":{"a":0,"k":[100,100],"ix":3},"r":{"a":0,"k":0,"ix":6},"o":{"a":0,"k":100,"ix":7},"sk":{"a":0,"k":0,"ix":4},"sa":{"a":0,"k":0,"ix":5},"nm":"Transform"}],"nm":"Group 5","np":4,"cix":2,"bm":0,"ix":5,"mn":"ADBE Vector Group","hd":false},{"ty":"gr","it":[{"ind":0,"ty":"sh","ix":1,"ks":{"a":0,"k":{"i":[[0.06,-3.467],[4.383,0],[0,0],[0.376,3.533],[-3.8,0.033]],"o":[[-0.047,2.653],[0,0],[-1.905,-0.403],[-0.231,-2.171],[4.263,-0.036]],"v":[[5.243,5.382],[0.41,8.296],[0.41,8.294],[-4.865,5.199],[0.857,1.799]],"c":true},"ix":2},"nm":"Path 1","mn":"ADBE Vector Shape - Group","hd":false},{"ind":1,"ty":"sh","ix":2,"ks":{"a":0,"k":{"i":[[0.018,3.986],[9,-1.128],[0.561,-6.84],[-0.133,-0.285],[-3.092,-0.407],[-0.794,-0.847],[0.174,-0.622],[0.562,0.058],[2.286,-0.323],[0.18,-4.3],[-5.194,-1.161],[-4.698,1.56],[0.031,1.453]],"o":[[-0.043,-9.012],[-6.921,0.867],[-0.007,0.092],[6.277,-1.996],[1.158,0.088],[0.46,0.454],[-0.266,0.852],[-2.297,-0.231],[-4.964,0.683],[-0.198,4.725],[4.855,0.964],[1.49,-0.441],[-0.085,-3.985]],"v":[[11.965,-1.717],[-1.878,-13.786],[-9.749,-5.68],[-9.534,-5.204],[1.622,-7.049],[4.656,-5.594],[5.12,-3.85],[3.535,-3.398],[-3.366,-3.26],[-11.84,4.962],[-4.393,13.951],[10.182,13.042],[12.008,10.242]],"c":true},"ix":2},"nm":"Path 2","mn":"ADBE Vector Shape - Group","hd":false},{"ty":"mm","mm":1,"nm":"Merge Paths 1","mn":"ADBE Vector Filter - Merge","hd":false},{"ty":"fl","c":{"a":0,"k":[0.732999973671,0.902000038297,0.016000001571,1],"ix":4},"o":{"a":0,"k":100,"ix":5},"r":1,"bm":0,"nm":"Fill 1","mn":"ADBE Vector Graphic - Fill","hd":false},{"ty":"tr","p":{"a":0,"k":[72.507,60.301],"ix":2},"a":{"a":0,"k":[0,0],"ix":1},"s":{"a":0,"k":[100,100],"ix":3},"r":{"a":0,"k":0,"ix":6},"o":{"a":0,"k":100,"ix":7},"sk":{"a":0,"k":0,"ix":4},"sa":{"a":0,"k":0,"ix":5},"nm":"Transform"}],"nm":"Group 6","np":4,"cix":2,"bm":0,"ix":6,"mn":"ADBE Vector Group","hd":false},{"ty":"gr","it":[{"ind":0,"ty":"sh","ix":1,"ks":{"a":0,"k":{"i":[[0.618,-0.002],[4.04,0],[-2.992,0.1],[-1.368,-3.871]],"o":[[-3.542,0.012],[1.408,-2.815],[3.266,-0.113],[-0.968,0.068]],"v":[[4.913,-3.889],[-6.21,-3.883],[-0.221,-8.507],[7.117,-4.039]],"c":true},"ix":2},"nm":"Path 1","mn":"ADBE Vector Shape - Group","hd":false},{"ind":1,"ty":"sh","ix":2,"ks":{"a":0,"k":{"i":[[4.888,2.094],[3.969,-4.429],[-2.531,-5.318],[-9.047,4.132],[1.6,1.575],[4,-1.951],[1.883,-0.06],[1.82,3.043],[-1.683,-0.027],[-2.827,0],[0,0],[-2.824,-0.09],[-0.047,1.347]],"o":[[-5.435,-2.414],[-3.833,4.472],[3.99,7.584],[1.274,-0.58],[-1.181,-1.161],[-1.711,0.79],[-3.083,0.127],[-0.724,-1.211],[2.826,0.046],[0,0],[2.827,0],[1.396,0.044],[0.199,-5.732]],"v":[[6.13,-13.52],[-9.645,-10.141],[-11.785,5.96],[10.331,11.803],[11.63,9.044],[7.723,5.729],[2.277,7.016],[-5.648,3.644],[-4.62,1.738],[3.861,1.751],[3.857,1.768],[12.337,1.795],[14.118,-0.012]],"c":true},"ix":2},"nm":"Path 2","mn":"ADBE Vector Shape - Group","hd":false},{"ty":"mm","mm":1,"nm":"Merge Paths 1","mn":"ADBE Vector Filter - Merge","hd":false},{"ty":"fl","c":{"a":0,"k":[0.732999973671,0.902000038297,0.016000001571,1],"ix":4},"o":{"a":0,"k":100,"ix":5},"r":1,"bm":0,"nm":"Fill 1","mn":"ADBE Vector Graphic - Fill","hd":false},{"ty":"tr","p":{"a":0,"k":[14.567,61.1],"ix":2},"a":{"a":0,"k":[0,0],"ix":1},"s":{"a":0,"k":[100,100],"ix":3},"r":{"a":0,"k":0,"ix":6},"o":{"a":0,"k":100,"ix":7},"sk":{"a":0,"k":0,"ix":4},"sa":{"a":0,"k":0,"ix":5},"nm":"Transform"}],"nm":"Group 7","np":4,"cix":2,"bm":0,"ix":7,"mn":"ADBE Vector Group","hd":false},{"ty":"gr","it":[{"ind":0,"ty":"sh","ix":1,"ks":{"a":0,"k":{"i":[[2.278,-1.161],[1.774,2.117],[-2.109,2.976],[-2.4,-1.206],[-0.052,-0.973],[0,-1.46],[0.071,-0.622]],"o":[[-2.632,1.343],[-2.156,-2.942],[1.797,-2.216],[1.249,0.628],[0.077,1.456],[0.057,0.623],[-0.383,1.788]],"v":[[5.441,11.627],[-4.122,9.541],[-4.201,-0.369],[5.637,-2.695],[6.548,0.057],[6.568,4.436],[6.548,6.308]],"c":true},"ix":2},"nm":"Path 1","mn":"ADBE Vector Shape - Group","hd":false},{"ind":1,"ty":"sh","ix":2,"ks":{"a":0,"k":{"i":[[0,11.818],[1.607,-0.716],[-0.282,-1.061],[3.237,0.115],[0.457,-7.913],[-7.814,-1],[-3.786,0.876],[0,1.379]],"o":[[-2.102,1.165],[-1.052,0.312],[0.745,3.733],[-8.331,-0.294],[-0.444,7.696],[3.864,0.409],[1.13,-0.233],[-0.037,-11.393]],"v":[[13.109,-18.883],[7.904,-16.04],[6.52,-13.574],[2.258,-9.641],[-12.687,3.705],[-0.286,18.474],[11.27,17.768],[13.13,15.717]],"c":true},"ix":2},"nm":"Path 2","mn":"ADBE Vector Shape - Group","hd":false},{"ty":"mm","mm":1,"nm":"Merge Paths 1","mn":"ADBE Vector Filter - Merge","hd":false},{"ty":"fl","c":{"a":0,"k":[0.732999973671,0.902000038297,0.016000001571,1],"ix":4},"o":{"a":0,"k":100,"ix":5},"r":1,"bm":0,"nm":"Fill 1","mn":"ADBE Vector Graphic - Fill","hd":false},{"ty":"tr","p":{"a":0,"k":[130.752,56.135],"ix":2},"a":{"a":0,"k":[0,0],"ix":1},"s":{"a":0,"k":[100,100],"ix":3},"r":{"a":0,"k":0,"ix":6},"o":{"a":0,"k":100,"ix":7},"sk":{"a":0,"k":0,"ix":4},"sa":{"a":0,"k":0,"ix":5},"nm":"Transform"}],"nm":"Group 8","np":4,"cix":2,"bm":0,"ix":8,"mn":"ADBE Vector Group","hd":false},{"ty":"gr","it":[{"ind":0,"ty":"sh","ix":1,"ks":{"a":0,"k":{"i":[[1.047,-1.869],[3.01,-1.3],[0.045,1.26],[0.068,1.044],[0,0],[-2.309,1.442],[-1.883,-1.044]],"o":[[-1.694,3.022],[-1.165,0.504],[-0.039,-1.046],[0,0],[-0.071,-2.369],[2.067,-1.291],[1.715,0.955]],"v":[[-14.991,3.975],[-22.471,9.891],[-24.284,8.637],[-24.484,5.503],[-24.485,5.503],[-22.094,-0.577],[-16.152,-0.225]],"c":true},"ix":2},"nm":"Path 1","mn":"ADBE Vector Shape - Group","hd":false},{"ind":1,"ty":"sh","ix":2,"ks":{"a":0,"k":{"i":[[-0.138,4.363],[-0.215,5.869],[1.437,0.067],[-0.108,-2.876],[0.035,-5.037],[3.447,-0.108],[0.266,3.921],[0,2.623],[4.489,-0.025],[-0.062,-1.542],[0.009,-2.519],[6.528,0.067],[-0.047,1.821],[-0.14,4.193],[2.119,-0.4],[-0.149,-3.63],[-0.082,-4.406],[1.568,0.02],[6.367,0],[-1.23,3.175],[2.572,1.939],[3.915,0.04],[1.595,-4.578],[0.064,-2.098],[2,-1.457],[2.6,-0.224],[-0.035,2.313],[-0.152,8.812],[1.707,-0.248],[-0.058,-3.5],[0.119,-11.226],[-1.956,0],[-20.252,0],[-2.653,2.369],[-0.96,-0.882],[-4.667,1.644]],"o":[[0.186,-5.871],[0.112,-3.035],[-1.582,-0.073],[0.189,5.03],[-0.029,4.172],[-3.369,0.1],[-0.177,-2.612],[-0.003,-4.483],[-1.788,0.01],[0.102,2.514],[-0.022,6.482],[-2.05,-0.021],[0.107,-4.19],[0.069,-2.045],[-1.659,0.311],[0.186,4.4],[0.028,1.443],[-5.639,-0.074],[2.82,-2.952],[1.252,-3.232],[-3.031,-2.478],[-4.859,0.058],[-0.607,2.01],[-0.187,2.538],[-1.728,1.258],[-2.408,0.211],[0.131,-8.813],[0.042,-2.44],[-1.55,0.224],[0.188,11.224],[-0.021,2.169],[20.255,-0.05],[3.422,0],[1.253,-1.12],[4.069,3.74],[4.352,-1.532]],"v":[[47.503,8.247],[47.749,-9.375],[44.384,-11.475],[41.084,-9.211],[41.123,5.898],[35.857,12.321],[29.971,6.321],[29.922,-1.546],[25.433,-5.887],[23.404,-3.695],[23.43,3.859],[15.108,11.859],[12.708,9.307],[12.782,-3.283],[10.158,-5.861],[6.072,-3.402],[6.158,9.817],[4.264,11.85],[-13.384,11.821],[-7.215,3.116],[-9.115,-5.123],[-19.846,-9.013],[-29.58,-2.066],[-30.59,4.123],[-30.684,11.47],[-38.35,11.87],[-41.305,8.87],[-41.189,-17.571],[-44.053,-19.871],[-47.803,-17.521],[-47.803,16.159],[-45.103,18.739],[15.652,18.724],[25.052,15.866],[27.82,16.222],[41.411,18.032]],"c":true},"ix":2},"nm":"Path 2","mn":"ADBE Vector Shape - Group","hd":false},{"ty":"mm","mm":1,"nm":"Merge Paths 1","mn":"ADBE Vector Filter - Merge","hd":false},{"ty":"fl","c":{"a":0,"k":[0.732999973671,0.902000038297,0.016000001571,1],"ix":4},"o":{"a":0,"k":100,"ix":5},"r":1,"bm":0,"nm":"Fill 1","mn":"ADBE Vector Graphic - Fill","hd":false},{"ty":"tr","p":{"a":0,"k":[81.329,21.271],"ix":2},"a":{"a":0,"k":[0,0],"ix":1},"s":{"a":0,"k":[100,100],"ix":3},"r":{"a":0,"k":0,"ix":6},"o":{"a":0,"k":100,"ix":7},"sk":{"a":0,"k":0,"ix":4},"sa":{"a":0,"k":0,"ix":5},"nm":"Transform"}],"nm":"Group 9","np":6,"cix":2,"bm":0,"ix":9,"mn":"ADBE Vector Group","hd":false}],"ip":0,"op":900.000036657751,"st":0,"bm":0}],"markers":[]}